melder/melder.py
melder-0.1.0.dist-info/licenses/LICENSE
melder-0.1.0.dist-info/licenses/NOTICE
melder-0.1.0.dist-info/METADATA
melder-0.1.0.dist-info/WHEEL
melder-0.1.0.dist-info/top_level.txt
melder-0.1.0.dist-info/RECORD
